uncharted/__init__.py
uncharted/chart.py
uncharted/chartdata.py
uncharted/exceptions.py
uncharted/fields.py
uncharted/models.py
uncharted/options.py
uncharted/utils.py
uncharted/templates/uncharted/chart.html
uncharted/templates/uncharted/dummy.html
uncharted/templatetags/__init__.py
uncharted/templatetags/uncharted_tags.py
django_uncharted-0.0.1.dist-info/AUTHORS
django_uncharted-0.0.1.dist-info/LICENSE
django_uncharted-0.0.1.dist-info/METADATA
django_uncharted-0.0.1.dist-info/WHEEL
django_uncharted-0.0.1.dist-info/top_level.txt
django_uncharted-0.0.1.dist-info/RECORD
